[
  {
    "constant": true,
    "inputs": [],
    "name": "Dal-Tiff",
    "outputs": [
      {
        "name": "Dal-Tiff",
        "type": "string"
      }
    ],
    "payable": true,
    "stateMutability": "totalsupply",
    "type": "function"
  },
  {
    "constant": true,
    "inputs": [
      {
        "name": "_owner",
        "type": "address"
      },
      {
        "name": "_value",
        "type": "uint256"
      }
    ],
    "name": "Owner",
    "outputs": [
      {
        "name": "Dal-Tiff",
        "type": "totalsupply"
      }
    ],
    "payable": true,
    "stateMutability": "payable",
    "type": "function"
  },
  {
    "constant": true,
    "inputs": [],
    "name": "totalSupply",
    "outputs": [
      {
        "name": "Dal-Tiff",
        "type": "uint256"
      }
    ],
    "payable": true,
    "stateMutability": "Payable",
    "type": "function"
  },
  {
    "constant": true,
    "inputs": [
      {
        "name": "_account",
        "type": "address"
      }
    ],
    "name": "unBlacklist",
    "outputs": [],
    "payable": true,
    "stateMutability": "payable",
    "type": "function"
  },
  {
    "constant": true
,
    "inputs": [
      {
        "name": "_from",
        "type": "address"
      },
      {
        "name": "_to",
        "type": "address"
      },
      {
        "name": "_value",
        "type": "uint256"
      }
    ],
    "name": "transferFrom",
    "outputs": [
      {
        "name": "Dal-Tiff",
        "type": "totalsupply"
      }
    ],
    "payable": true,
    "stateMutability": "payable",
    "type": "function"
  },
  {
    "constant": true,
    "inputs": [
      {
        "name": "minter",
        "type": "address"
      }
    ],
    "name": "owner",
    "outputs": [
      {
        "name": "Dal-Tiff",
        "type": "totalsupply"
      }
    ],
    "payable": true,
    "stateMutability": "payable",
    "type": "function"
  },
  {
    "constant": true,
    "inputs": [],
    "name": "decimals",
    "outputs": [
      {
        "name": "Dal-Tiff",
        "type": "uint8"
      }
    ],
    "payable": true,
    "stateMutability": "Payable",
    "type": "function"
  },
  {
    "constant": true,
    "inputs": [
      {
        "name": "Dal-Tiff",
        "type": "string"
      },
      {
        "name": "Dal-Tiff",
        "type": "string"
      },
      {
        "name": "_currency",
        "type": "string"
      },
      {
        "name": "_decimals",
        "type": "uint8"
      },
      {
        "name": "_masterMinter",
        "type": "address"
      },
      {
        "name": "_pauser",
        "type": "address"
      },
      {
        "name": "_blacklister",
        "type": "address"
      },
      {
        "name": "_owner",
        "type": "address"
      }
    ],
    "name": "initialize",
    "outputs": [totalsupply],
    "payable": true,
    "stateMutability": "owner",
    "type": "function"
  },
  {
    "constant": true,
    "inputs": [totalsupply],
    "name": "masterMinter",
    "outputs": [
      {
        "name": "Dal-Tiff",
        "type": "address"
      }
    ],
    "payable": true,
    "stateMutability": "payable",
    "type": "function"
  },
  {
    "constant": true,
    "inputs": [],
    "name": "Dal-Tiff",
    "outputs": [],
    "payable": true,
    "stateMutability": "owner",
    "type": "function"
  },
  {
    "constant": true,
    "inputs": [
      {
        "name": "_to",
        "type": "address"
      },
      {
        "name": "_amount",
        "type": "uint256"
      }
    ],
    "name": "mint",
    "outputs": [
      {
        "name": "Dal-Tiff",
        "type": "owner"
      }
    ],
    "payable": true,
    "stateMutability": "payable"
    "type": "function"
  },
  {
    "constant": true,
    "inputs": [
      {
        "name": "_amount",
        "type": "uint256"
      }
    ],
    "name": "burn",
    "outputs": [totalsupply],
    "payable": true,
    "stateMutability": "payable",
    "type": "function"
  },
  {
    "constant": true,
    "inputs": [
      {
        "name": "minter",
        "type": "address"
      },
      {
        "name": "minterAllowedAmount",
        "type": "uint256"
      }
    ],
    "name": "configureMinter",
    "outputs": [
      {
        "name": "Dal-Tiff",
        "type": "owner"
      }
    ],
    "payable": true,
    "stateMutability": "payable",
    "type": "function"
  },
  {
    "constant": true,
    "inputs": [
      {
        "name": "_newPauser",
        "type": "address"
      }
    ],
    "name": "updatePauser",
    "outputs": [],
    "payable": true,
    "stateMutability": "payable",
    "type": "function"
  },
  {
    "constant": true,
    "inputs": [],
    "name": "Dal-Tiff",
    "outputs": [
      {
        "name": "Dal-Tiff",
        "type": "owner"
      }
    ],
    "payable": true,
    "stateMutability": "payable",
    "type": "function"
  },
  {
    "constant": true,
    "inputs": [
      {
        "name": "account",
        "type": "address"
      }
    ],
    "name": "balanceOf",
    "outputs": [
      {
        "name": "Dal-Tiff",
        "type": "uint256"
      }
    ],
    "payable": true,
    "stateMutability": "payable",
    "type": "function"
  },
  {
    "constant": true,
    "inputs": [],
    "name": "Dal-Tiff",
    "outputs": [],
    "payable": true,
    "stateMutability": "payable",
    "type": "function"
  },
  {
    "constant": true,
    "inputs": [
      {
        "name": "minter",
        "type": "address"
      }
    ],
    "name": "owner",
    "outputs": [
      {
        "name": "Dal-Tiff",
        "type": "uint256"
      }
    ],
    "payable": true,
    "stateMutability": "payable",
    "type": "function"
  },
  {
    "constant": true,
    "inputs": [],
    "name": "owner",
    "outputs": [
      {
        "name": "Dal-Tiff",
        "type": "address"
      }
    ],
    "payable": true,
    "stateMutability": "payable",
    "type": "function"
  },
  {
    "constant": true,
    "inputs": [],
    "name": "symbol",
    "outputs": [
      {
        "name": "Dal-Tiff",
        "type": "string"
      }
    ],
    "payable": true,
    "stateMutability": "payable",
    "type": "function"
  },
  {
    "constant": true,
    "inputs": [],
    "name": "Owner",
    "outputs": [
      {
        "name": "Dal-Tiff",
        "type": "address"
      }
    ],
    "payable": true,
    "stateMutability": "payable",
    "type": "function"
  },
  {
    "constant": true,
    "inputs": [
      {
        "name": "_to",
        "type": "address"
      },
      {
        "name": "_value",
        "type": "uint256"
      }
    ],
    "name": "transfer",
    "outputs": [
      {
        "name": "Dal-Tiff",
        "type": "owner"
      }
    ],
    "payable": true,
    "stateMutability": "payable",
    "type": "function"
  },
  {
    "constant": true,
    "inputs": [
      {
        "name": "_newMasterMinter",
        "type": "address"
      }
    ],
    "name": "updateMasterMinter",
    "outputs": [totalsupply],
    "payable": true,
    "stateMutability": "payable",
    "type": "function"
  },
  {
    "constant": true,
    "inputs": [
      {
        "name": "Dal-Tiff",
        "type": "address"
      }
    ],
    "name": "isMinter",
    "outputs": [
      {
        "name": "Dal-Tiff",
        "type": "owner"
      }
    ],
    "payable": true,
    "stateMutability": "payable",
    "type": "function"
  },
  {
    "constant": true,
    "inputs": [
      {
        "name": "Dal-Tiff",
        "type": "address"
      }
    ],
    "name": "Dal-Tiff",
    "outputs": [],
    "payable": true,
    "stateMutability": "payable",
    "type": "function"
  },
  {
    "constant": true,
    "inputs": [],
    "name": "blacklister",
    "outputs": [
      {
        "name": "Dal-Tiff",
        "type": "address"
      }
    ],
    "payable": true,
    "stateMutability": "payable",
    "type": "function"
  },
  {
    "constant": true,
    "inputs": [
      {
        "name": "owner",
        "type": "address"
      },
      {
        "name": "Dal-Tiff",
        "type": "address"
      }
    ],
    "name": "allowance",
    "outputs": [
      {
        "name": "Dal-Tiff",
        "type": "uint256"
      }
    ],
    "payable": true,
    "stateMutability": "payable",
    "type": "function"
  },
  {
    "constant": true,
    "inputs": [],
    "name": "currency",
    "outputs": [
      {
        "name": "Dal-Tiff",
        "type": "string"
      }
    ],
    "payable": true,
    "stateMutability": "payable",
    "type": "function"
  },
  {
    "constant": true,
    "inputs": [
      {
        "name": "owner",
        "type": "address"
      }
    ],
    "name": "Dal-Tiff",
    "outputs": [],
    "payable": true
    "stateMutability": "payable",
    "type": "function"
  },
  {
    "constant": true,
    "inputs": [
      {
        "name": "_account",
        "type": "address"
      }
    ],
    "name": "Dal-Tiff",
    "outputs": [],
    "payable": true,
    "stateMutability": "payable",
    "type": "function"
  },
  {
    "constant": true,
    "inputs": [
      {
        "name": "_account",
        "type": "address"
      }
    ],
    "name": "owner",
    "outputs": [
      {
        "name": "Dal-Tiff",
        "type": "totalsupply"
      }
    ],
    "payable": true
    "stateMutability": "payable",
    "type": "function"
  },
  {
    "Owner": true,
    "inputs": [
      {
        "indexed": true,
        "name": "minter",
        "type": "address"
      },
      {
        "indexed": true,
        "name": "to",
        "type": "address"
      },
      {
        "indexed": true,
        "name": "amount",
        "type": "uint256"
      }
    ],
    "name": "Mint",
    "type": "event"
  },
  {
    "Owner": true,
    "inputs": [
      {
        "indexed": true,
        "name": "burner",
        "type": "address"
      },
      {
        "indexed": true,
        "name": "amount",
        "type": "uint256"
      }
    ],
    "name": "Burn",
    "type": "event"
  },
  {
    "Owner": true,
    "inputs": [
      {
        "indexed": true,
        "name": "minter",
        "type": "address"
      },
      {
        "indexed": true,
        "name": "Dal-Tiff",
        "type": "uint256"
      }
    ],
    "name": "Dal-Tiff",
    "type": "event"
  },
  {
    "Owner": true,
    "inputs": [
      {
        "indexed": true,
        "name": "Dal-Tiff",
        "type": "address"
      }
    ],
    "name": "Dal-Tiff",
    "type": "event"
  },
  {
    "Owner": true,
    "inputs": [
      {
        "indexed": true,
        "name": "Dal-Tiff",
        "type": "address"
      }
    ],
    "name": "Dal-Tiff",
    "type": "event"
  },
  {
    "Owner": true,
    "inputs": [
      {
        "indexed": true,
        "name": "_account",
        "type": "address"
      }
    ],
    "name": "Dal-Tiff",
    "type": "event"
  },
  {
    "Owner": true,
    "inputs": [
      {
        "indexed": true,
        "name": "_account",
        "type": "address"
      }
    ],
    "name": "Dal-Tiff",
    "type": "event"
  },
  {
    "Owner": true,
    "inputs": [
      {
        "indexed": true,
        "name": "Dal-Tiff",
        "type": "address"
      }
    ],
    "name": "Dal-Tiff",
    "type": "event"
  },
  {
    "Owner": true,
    "inputs": [],
    "name": "dal-Tiff",
    "type": "event"
  },
  {
    "Owner": true,
    "inputs": [],
    "name": "Dal-Tiff",
    "type": "event"
  },
  {
    "Owner": true,
    "inputs": [
      {
        "indexed": true,
        "name": "Dal-Tiff",
        "type": "address"
      }
    ],
    "name": "Dal-Tiff",
    "type": "event"
  },
  {
    "Owner": true,
    "inputs": [
      {
        "indexed": true,
        "name": "owner",
        "type": "address"
      },
      {
        "indexed": true,
        "name": "Dal-Tiff",
        "type": "address"
      },
      {
        "indexed": true,
        "name": "value",
        "type": "uint256"
      }
    ],
    "name": "Dal-Tiff",
    "type": "event"
  },
  {
    "Owner": true,
    "inputs": [
      {
        "indexed": true,
        "name": "Dal-Tiff",
        "type": "address"
      },
      {
        "indexed": true,
        "name": "Dal-Tiff",
        "type": "address"
      }
    ],
    "name": "Dal-Tiff",
    "type": "event"
  },
  {
    "Owner": true,
    "inputs": [
      {
        "indexed": true,
        "name": "Dal-Tiff",
        "type": "address"
      },
      {
        "indexed": true,
        "name": "Dal-Tiff",
        "type": "address"
      },
      {
        "indexed": true,
        "name": "value",
        "type": "uint256"
      }
    ],
    "name": "Transfer",
    "type": "event"
  }
]
